<!-- AUTO-GENERATED from .tributors.credit.yaml by render_credit.py -->
<contrib-group>
  <contrib contrib-type="author">
    <string-name>
      <given-names>Austin</given-names>
      <surname>Macdonald</surname>
    </string-name>
    <contrib-id contrib-id-type="orcid">https://orcid.org/0000-0002-8124-807X</contrib-id>
    <role vocab="credit" vocab-identifier="https://credit.niso.org/" vocab-term="Methodology" vocab-term-identifier="https://credit.niso.org/contributor-roles/methodology/">Methodology</role>
    <role vocab="credit" vocab-identifier="https://credit.niso.org/" vocab-term="Software" vocab-term-identifier="https://credit.niso.org/contributor-roles/software/">Software</role>
    <role vocab="credit" vocab-identifier="https://credit.niso.org/" vocab-term="Resources" vocab-term-identifier="https://credit.niso.org/contributor-roles/resources/">Resources</role>
    <role vocab="credit" vocab-identifier="https://credit.niso.org/" vocab-term="Writing – original draft" vocab-term-identifier="https://credit.niso.org/contributor-roles/writing-original-draft/">Writing – original draft</role>
    <role vocab="credit" vocab-identifier="https://credit.niso.org/" vocab-term="Writing – review &amp; editing" vocab-term-identifier="https://credit.niso.org/contributor-roles/writing-review-editing/">Writing – review &amp; editing</role>
  </contrib>
  <contrib contrib-type="author">
    <string-name>
      <given-names>Cody C.</given-names>
      <surname>Baker</surname>
    </string-name>
    <contrib-id contrib-id-type="orcid">https://orcid.org/0000-0002-0829-4790</contrib-id>
    <role vocab="credit" vocab-identifier="https://credit.niso.org/" vocab-term="Conceptualization" vocab-term-identifier="https://credit.niso.org/contributor-roles/conceptualization/">Conceptualization</role>
    <role vocab="credit" vocab-identifier="https://credit.niso.org/" vocab-term="Methodology" vocab-term-identifier="https://credit.niso.org/contributor-roles/methodology/">Methodology</role>
    <role vocab="credit" vocab-identifier="https://credit.niso.org/" vocab-term="Software" vocab-term-identifier="https://credit.niso.org/contributor-roles/software/">Software</role>
    <role vocab="credit" vocab-identifier="https://credit.niso.org/" vocab-term="Visualization" vocab-term-identifier="https://credit.niso.org/contributor-roles/visualization/">Visualization</role>
    <role vocab="credit" vocab-identifier="https://credit.niso.org/" vocab-term="Writing – original draft" vocab-term-identifier="https://credit.niso.org/contributor-roles/writing-original-draft/">Writing – original draft</role>
    <role vocab="credit" vocab-identifier="https://credit.niso.org/" vocab-term="Writing – review &amp; editing" vocab-term-identifier="https://credit.niso.org/contributor-roles/writing-review-editing/">Writing – review &amp; editing</role>
  </contrib>
  <contrib contrib-type="author">
    <string-name>
      <given-names>Isaac</given-names>
      <surname>To</surname>
    </string-name>
    <contrib-id contrib-id-type="orcid">https://orcid.org/0000-0002-4740-0824</contrib-id>
    <role vocab="credit" vocab-identifier="https://credit.niso.org/" vocab-term="Validation" vocab-term-identifier="https://credit.niso.org/contributor-roles/validation/">Validation</role>
    <role vocab="credit" vocab-identifier="https://credit.niso.org/" vocab-term="Writing – review &amp; editing" vocab-term-identifier="https://credit.niso.org/contributor-roles/writing-review-editing/">Writing – review &amp; editing</role>
  </contrib>
  <contrib contrib-type="author">
    <string-name>
      <given-names>Yaroslav O.</given-names>
      <surname>Halchenko</surname>
    </string-name>
    <contrib-id contrib-id-type="orcid">https://orcid.org/0000-0003-3456-2493</contrib-id>
    <role vocab="credit" vocab-identifier="https://credit.niso.org/" vocab-term="Conceptualization" vocab-term-identifier="https://credit.niso.org/contributor-roles/conceptualization/">Conceptualization</role>
    <role vocab="credit" vocab-identifier="https://credit.niso.org/" vocab-term="Funding acquisition" vocab-term-identifier="https://credit.niso.org/contributor-roles/funding-acquisition/">Funding acquisition</role>
    <role vocab="credit" vocab-identifier="https://credit.niso.org/" vocab-term="Supervision" vocab-term-identifier="https://credit.niso.org/contributor-roles/supervision/" specific-use="lead">Supervision</role>
    <role vocab="credit" vocab-identifier="https://credit.niso.org/" vocab-term="Project administration" vocab-term-identifier="https://credit.niso.org/contributor-roles/project-administration/">Project administration</role>
    <role vocab="credit" vocab-identifier="https://credit.niso.org/" vocab-term="Methodology" vocab-term-identifier="https://credit.niso.org/contributor-roles/methodology/">Methodology</role>
    <role vocab="credit" vocab-identifier="https://credit.niso.org/" vocab-term="Software" vocab-term-identifier="https://credit.niso.org/contributor-roles/software/">Software</role>
    <role vocab="credit" vocab-identifier="https://credit.niso.org/" vocab-term="Resources" vocab-term-identifier="https://credit.niso.org/contributor-roles/resources/">Resources</role>
    <role vocab="credit" vocab-identifier="https://credit.niso.org/" vocab-term="Writing – review &amp; editing" vocab-term-identifier="https://credit.niso.org/contributor-roles/writing-review-editing/">Writing – review &amp; editing</role>
  </contrib>
</contrib-group>
